LICENSE
README.md
setup.py
pdf12step/__init__.py
pdf12step/__main__.py
pdf12step/__version__.py
pdf12step/adict.py
pdf12step/cached.py
pdf12step/cli.py
pdf12step/client.py
pdf12step/config.py
pdf12step/flask_app.py
pdf12step/log.py
pdf12step/meetings.py
pdf12step/templating.py
pdf12step/utils.py
pdf12step.egg-info/PKG-INFO
pdf12step.egg-info/SOURCES.txt
pdf12step.egg-info/dependency_links.txt
pdf12step.egg-info/entry_points.txt
pdf12step.egg-info/requires.txt
pdf12step.egg-info/top_level.txt
pdf12step/templates/columns.html
pdf12step/templates/default.config.yaml
pdf12step/templates/layout.html
pdf12step/templates/macros.html
pdf12step/templates/table.html
pdf12step/templates/assets/css/columns.css
pdf12step/templates/assets/css/font.css
pdf12step/templates/assets/css/print.css
pdf12step/templates/assets/css/style.css
pdf12step/templates/assets/css/table.css
pdf12step/templates/assets/img/cover_background.svg
pdf12step/templates/includes/info.html
pdf12step/templates/includes/sections/backcover.html
pdf12step/templates/includes/sections/codes.html
pdf12step/templates/includes/sections/contact.html
pdf12step/templates/includes/sections/cover.html
pdf12step/templates/includes/sections/index.html
pdf12step/templates/includes/sections/list_1section.html
pdf12step/templates/includes/sections/list_2sections.html
pdf12step/templates/includes/sections/misc.html
pdf12step/templates/includes/sections/notes.html
pdf12step/templates/includes/sections/readings.html
pdf12step/templates/includes/sections/regions.html
tests/__init__.py
tests/base.py
tests/test_cli.py
tests/test_client.py
tests/test_meetings.py
tests/test_templating.py
tests/test_utils.py