Metadata-Version: 2.1
Name: pdf12step
Version: 1.4.0
Summary: Generates PDFs meeting guides from sites using the 12 Step Meeting List WordPress plugin
Home-page: https://github.com/justquick/pdf12step
Author: Justin Quick
Author-email: justquick@gmail.com
License: BSD
Project-URL: Documentation, https://pdf12step.readthedocs.io/
Project-URL: Source, https://github.com/justquick/pdf12step
Project-URL: Bug Tracker, https://github.com/justquick/pdf12step/issues
Project-URL: Wordpress Plugin, https://wordpress.org/plugins/12-step-meeting-list/
Platform: UNKNOWN
Classifier: Development Status :: 4 - Beta
Classifier: Programming Language :: Python :: 3
Classifier: License :: OSI Approved :: BSD License
Classifier: Operating System :: OS Independent
Classifier: Framework :: Flask
Classifier: Environment :: Console
Classifier: Topic :: Documentation :: Sphinx
Classifier: Topic :: Multimedia :: Graphics :: Presentation
Classifier: Topic :: Text Processing :: Markup :: HTML
Requires-Python: >=3.6
License-File: LICENSE
